manageritm/__init__.py
manageritm/app.py
manageritm/server/__init__.py
manageritm/server/client/__init__.py
manageritm/server/client/routes.py
manageritm/server/main/__init__.py
manageritm/server/main/routes.py
manageritm/server/process_minder.py
manageritm/server/processes.py
manageritm/server/scripts/har_dump.py
manageritm/server/utils.py
manageritm-0.4.0.dist-info/LICENSE
manageritm-0.4.0.dist-info/METADATA
manageritm-0.4.0.dist-info/WHEEL
manageritm-0.4.0.dist-info/entry_points.txt
manageritm-0.4.0.dist-info/RECORD
