Metadata-Version: 2.1
Name: manageritm
Version: 0.4.0
Summary: Manage processes via an HTTP based API
Home-page: http://github.com/dskard/manageritm
License: MIT
Author: dskard
Requires-Python: >=3.9,<4.0
Classifier: License :: OSI Approved :: MIT License
Classifier: Programming Language :: Python :: 3
Classifier: Programming Language :: Python :: 3.9
Classifier: Programming Language :: Python :: 3.10
Classifier: Programming Language :: Python :: 3.11
Requires-Dist: flask (>=2.2.5,<3.0.0)
Requires-Dist: jsonschema (>=4.18.6,<5.0.0)
Requires-Dist: mitmproxy (>=9.0.1,<10.0.0)
Requires-Dist: requests (>=2.27.1,<3.0.0)
Requires-Dist: urllib3 (>=1.26.16,<2.0.0)
Project-URL: Repository, http://github.com/dskard/manageritm
